Metadata-Version: 2.1
Name: arith-vamsikrishna
Version: 0.0.1
Summary: A package to compute Prime Factors
Home-page: UNKNOWN
Author: Vamsi Krishna Meda
Author-email: medav1@mymail.nku.edu
License: UNKNOWN
Platform: UNKNOWN
Classifier: Programming Language :: Python :: 3
Classifier: License :: OSI Approved :: MIT License
Classifier: Operating System :: OS Independent
